ganglion_biosensing/__init__.py
ganglion_biosensing/board/__init__.py
ganglion_biosensing/board/board.py
ganglion_biosensing/board/ganglion.py
ganglion_biosensing/hub/__init__.py
ganglion_biosensing/hub/hub_connection.py
ganglion_biosensing/util/__init__.py
ganglion_biosensing/util/bluetooth.py
ganglion_biosensing/util/constants/__init__.py
ganglion_biosensing/util/constants/ganglion.py
ganglion_biosensing-0.1.7.dist-info/LICENSE
ganglion_biosensing-0.1.7.dist-info/METADATA
ganglion_biosensing-0.1.7.dist-info/WHEEL
ganglion_biosensing-0.1.7.dist-info/top_level.txt
ganglion_biosensing-0.1.7.dist-info/RECORD
