Metadata-Version: 2.1
Name: ganglion-biosensing
Version: 0.1.7
Summary: Modern Python 3.7+ library for interfacing with the OpenBCI Ganglion biosensing board over BTLE.
Home-page: https://github.com/molguin92/ganglion-biosensing
Author: Manuel Olguin Munoz
Author-email: manuel@olguin.se
License: MIT
Download-URL: https://github.com/molguin92/ganglion-biosensing/archive/0.1.7.tar.gz
Keywords: device,control,eeg,emg,ekg,ads1299,openbci,ganglion
Platform: UNKNOWN
Classifier: Development Status :: 3 - Alpha
Classifier: Intended Audience :: Developers
Classifier: Topic :: Software Development :: Build Tools
Classifier: License :: OSI Approved :: MIT License
Classifier: Programming Language :: Python :: 3
Classifier: Programming Language :: Python :: 3.7
Requires-Dist: numpy
Requires-Dist: bitstring
Requires-Dist: bluepy
